maoc_support_functions/__init__.py
maoc_support_functions/representation.py
maoc_support_functions/supporting_functions.py
maoc_support_functions-0.0.8.dist-info/METADATA
maoc_support_functions-0.0.8.dist-info/WHEEL
maoc_support_functions-0.0.8.dist-info/licenses/LICENSE
maoc_support_functions-0.0.8.dist-info/RECORD
