Metadata-Version: 2.1
Name: maoc_support_functions
Version: 0.0.8
Summary: Functions for generating the MAOC representation.
Project-URL: Homepage, https://github.com/hits-ccc/MAOC
Author-email: Stiv Llenga <stiv.llenga@h-its.org>
License-File: LICENSE
Classifier: License :: OSI Approved :: MIT License
Classifier: Operating System :: OS Independent
Classifier: Programming Language :: Python :: 3
Requires-Python: >=3.7
